{
  "name": "Push Ups",
  "versions": [
    {
      "id":   "v1",
      "name": "Wall push ups"
    },
{
      "id":   "v2",
      "name": "Box push ups"
    },
    {
      "id":   "v3",
      "name": "Three quarter push ups"
    },
    {
      "id":   "v4",
      "name": "3/4 push ups + 5s eccentrics"
    },
    {
      "id":   "v5",
      "name": "3/4 push ups + 5s eccentrics"
    },
    {
      "id":   "v6",
      "name": "Elbows in push ups"
    },
    {
      "id":   "v7",
      "name": "Diamond push ups"
    },
    {
      "id":   "v8",
      "name": "Uneven push ups"
    },
    {
      "id":   "v9",
      "name": "Decline push ups"
    },
    {
      "id":   "v10",
      "name": "Decline elbows in push ups"
    },
    {
      "id":   "v11",
      "name": "Decline diamond push ups"
    },
    {
      "id":   "v12",
      "name": "Wall one arm push ups"
    },
    {
      "id":   "v13",
      "name": "Incline one arm push ups"
    },
    {
      "id":   "v14",
      "name": "One arm push ups"
    },
    {
      "id":   "v15",
      "name": "Decline one arm push ups"
    }
  ]
}
